INSTALL
MANIFEST.in
VERSION
setup.cfg
setup.py
dimbrowser/__init__.py
dimbrowser/dimbrowser.py
dimbrowser/dimbrowserwrapper.cpp
doc/guide/Makefile
doc/guide/conf.py
doc/guide/dimbrowser.txt
doc/guide/index.txt
doc/guide/install.txt
doc/guide/pydim-c.txt
doc/guide/tutorial.txt
pydim/__init__.py
pydim/debug.py
pydim.egg-info/PKG-INFO
pydim.egg-info/SOURCES.txt
pydim.egg-info/dependency_links.txt
pydim.egg-info/top_level.txt
src/dimcppmodule.cpp
src/dimmodule.cpp
src/dimmodule.cpp~
src/mutelocks.sh
src/pydim_utils.cpp
src/pydim_utils.h
src/pydimlock.c
src/unmutelocks.sh