Metadata-Version: 1.0
Name: pydim
Version: 2.1.0.419397
Summary: Python interface package for DIM C and C++ interfaces.
Home-page: http://lhcbdoc.web.cern.ch/lhcbdoc/pydim/index.html
Author: Niko Neufeld (originally by Radu Stoica)
Author-email: niko.neufeld@cern.ch
License: GPL
Platform: UNKNOWN
